type_inspector/__init__.py
type_inspector-1.2.2.dist-info/LICENSE
type_inspector-1.2.2.dist-info/WHEEL
type_inspector-1.2.2.dist-info/METADATA
type_inspector-1.2.2.dist-info/RECORD
